LICENSE.txt
README.rst
setup.py
ssd1306.py
micropython_ssd1306_driver.egg-info/PKG-INFO
micropython_ssd1306_driver.egg-info/SOURCES.txt
micropython_ssd1306_driver.egg-info/dependency_links.txt
micropython_ssd1306_driver.egg-info/top_level.txt