Metadata-Version: 2.1
Name: micropython-ssd1306-driver
Version: 1.0.2
Summary: MicroPython Library for SSD1306 OLED Displays with some simple shape drawing functions.
Home-page: https://github.com/PerfecXX/MicroPython-SSD1306
Author: Teeraphat Kullanankanjana
Author-email: ku.teeraphat@hotmail.com
Maintainer: Teeraphat Kullanankanjana
Maintainer-email: ku.teeraphat@hotmail.com
License: MIT
Keywords: oled,ssd1306,esp32,micropython
Platform: UNKNOWN
Classifier: Development Status :: 3 - Alpha
Classifier: Programming Language :: Python :: Implementation :: MicroPython
Classifier: License :: OSI Approved :: MIT License
License-File: LICENSE.txt
